src/__init__.py
src/prompt_template_assembler.py
src/prompt_template_unit.py
prompt_template_assembler-0.0.1.dist-info/METADATA
prompt_template_assembler-0.0.1.dist-info/WHEEL
prompt_template_assembler-0.0.1.dist-info/top_level.txt
prompt_template_assembler-0.0.1.dist-info/RECORD
